{
  "name": "IDOUX", 
  "firstname": "Etienne",
  "image": "etienne-big.jpg",
  "thumbnail": "etienne-thumbnail.png",
  "bio": "lorem",
  "cv_fr": "etienne-cv-fr.pdf",
  "cv_en": "etienne-cv-en.pdf",
  "fonction": "label.perso.member",
  "metier": "label.perso.dev.web",
  "socials": [
    {
      "name": "mail",
      "link": "etienne.idoux@gmail.com",
      "icon": "fas fa-envelope"
    },
    {
      "name": "tel",
      "link": "07 77 31 11 11",
      "icon": "fas fa-phone"
    },
    {
      "name": "github",
      "link": "https://github.com/Rascaleuh",
      "icon": "fab fa-github"
    },
    {
      "name": "linkedin",
      "link": "https://www.linkedin.com/in/etienne-idoux",
      "icon": "fab fa-linkedin"
    }
  ],
  "studies": [
    {
      "title": "label.perso.studies.title.master2.tiw",
      "date": "label.perso.date.2020.2021",
      "location": "label.perso.location.lyon1",
      "logo": "lyon1.png",
      "list": []
    },
    {
      "title": "label.perso.studies.title.master1",
      "date": "label.perso.date.2019.2020",
      "location": "label.perso.location.lyon1",
      "logo": "lyon1.png",
      "list": [
        "label.perso.elem.dev.vue",
        "label.perso.elem.dev.node",
        "label.perso.elem.dev.python",
        "label.perso.elem.project.management.agile",
        "label.perso.elem.dev.java.spring"
      ]
    },
    {
      "title": "label.perso.studies.title.bachelor",
      "date": "label.perso.date.2015.2019",
      "location": "label.perso.location.orleans",
      "logo": "orleans.png",
      "list": [
        "label.perso.elem.dev.java.spring",
        "label.perso.elem.dev.symfony",
        "label.perso.elem.design.patterns",
        "label.perso.elem.basis.computer.science"
      ]
    },
    {
      "title": "label.perso.studies.title.bac",
      "date": "label.perso.date.2015",
      "location": "label.perso.location.balzac",
      "logo": "",
      "list": []
    }
  ],
  "experiences": [
    {
      "title": "label.perso.dev.web",
      "date": "label.perso.date.since.2020",
      "company": "Association La Cruz",
      "logo": "cruz.png",
      "list": [
        "label.perso.elem.web.project",
        "label.perso.elem.project.management",
        "label.perso.elem.teamwork"
      ]
    },
    {
      "title": "label.perso.exp.title.dev.intern",
      "date": "label.perso.date.march.august.2019",
      "company": "Qualnet",
      "logo": "qualNet.png",
      "list": [
        "label.perso.elem.scrum",
        "label.perso.elem.dotnet",
        "label.perso.elem.flexibility"
      ]
    },
    {
      "title": "label.perso.exp.title.production.agent",
      "date": "label.perso.date.2014.2016",
      "company": "Sermat",
      "logo": "sermat.png",
      "list": [
        "label.perso.elem.initialization.work.world",
        "label.perso.elem.rigor",
        "label.perso.elem.autonomy"
      ]
    }
  ],
  "projects": [
    "Only Vert",
    "Eva Dalla Costa",
    "Nova",
    "La Cruz",
    "Beautiful Lives",
    "Eco-potager",
    "Fix-it"
  ],
  "technologies": [
    "ReactJS",
    "VueJS",
    "NodeJS",
    "SASS",
    "HTML",
    "CSS",
    "JavaScript",
    "Git",
    "Java",
    "Spring",
    "C++",
    "CSharp",
    "SQL"
  ],
  "tools": [
    "Github",
    "Gitlab",
    "Postman",
    "Netlify",
    "Nginx",
    "Firebase",
    "Unity",
    "Figma",
    "VSCode",
    "Photoshop",
    "Linux",
    "Webpack"
  ],
  "qualities": [
    "label.perso.elem.flexibility",
    "label.perso.elem.autonomy",
    "label.perso.elem.teamwork",
    "label.perso.elem.project.management.agile"
  ]
}
